{"summaries":[{"symbol":{"__symbol":0},"metadata":{"__symbolic":"class"}},{"symbol":{"__symbol":1},"metadata":[{"id":"dash-board","url":"prehled","name":"Aktuálně","optional":false},{"id":"expenditure-viz","url":"rozpocet","name":"Rozpočet a výdaje","optional":true},{"id":"expenditure-events","url":"investicni-akce","name":"Investice","optional":true},{"id":"notice-board","url":"uredni-deska","name":"Úřední deska","optional":true},{"id":"contract-list","url":"registr-smluv","name":"Registr smluv","optional":true},{"id":"data-sources","url":"datove-zdroje","name":"Datové zdroje","optional":false},{"id":"admin","url":"admin","name":"Administrace","optional":false}]}],"symbols":[{"__symbol":0,"name":"Module","filePath":"/root/Supervizor-Plus/src/shared/data/modules.d.ts"},{"__symbol":1,"name":"MODULES","filePath":"/root/Supervizor-Plus/src/shared/data/modules.d.ts"}]}